pyqt_get_selected_filter/__init__.py
pyqt_get_selected_filter/getSelectedFilter.py
pyqt_get_selected_filter-0.0.1.dist-info/LICENSE
pyqt_get_selected_filter-0.0.1.dist-info/METADATA
pyqt_get_selected_filter-0.0.1.dist-info/WHEEL
pyqt_get_selected_filter-0.0.1.dist-info/top_level.txt
pyqt_get_selected_filter-0.0.1.dist-info/RECORD
