Metadata-Version: 2.1
Name: pyqt-get-selected-filter
Version: 0.0.1
Summary: Get selected filter string for QFileDialog
Home-page: https://github.com/yjg30737/pyqt-get-selected-filter.git
Author: Jung Gyu Yoon
Author-email: yjg30737@gmail.com
License: MIT
Platform: UNKNOWN
License-File: LICENSE
